[
  {
    "repo": "AscendAI",
    "stars": 2,
    "forks": 2,
    "watchers": 2,
    "open_issues": 0,
    "language": "Python",
    "size_kb": 1635364,
    "default_branch": "master",
    "updated_at": "2025-07-16T19:47:21Z",
    "clones": 328,
    "uniques": 79,
    "views": 1044,
    "visitors": 37,
    "pulls_count": 0,
    "fetched": "2025-07-16T21:01:00.249999"
  },
  {
    "repo": "Mobile-Developer",
    "stars": 5,
    "forks": 1,
    "watchers": 2,
    "open_issues": 0,
    "language": "Go",
    "size_kb": 30224,
    "default_branch": "master",
    "updated_at": "2025-07-14T04:10:25Z",
    "clones": 58,
    "uniques": 54,
    "views": 206,
    "visitors": 11,
    "pulls_count": 0,
    "fetched": "2025-07-16T21:01:01.291281"
  },
  {
    "repo": "AscendDocs-of-GovSeverance",
    "stars": 3,
    "forks": 0,
    "watchers": 2,
    "open_issues": 0,
    "language": null,
    "size_kb": 3914,
    "default_branch": "master",
    "updated_at": "2025-07-13T17:56:34Z",
    "clones": 31,
    "uniques": 26,
    "views": 73,
    "visitors": 3,
    "pulls_count": 0,
    "fetched": "2025-07-16T21:01:01.951261"
  },
  {
    "repo": "GodCore",
    "stars": 4,
    "forks": 0,
    "watchers": 2,
    "open_issues": 0,
    "language": "Python",
    "size_kb": 26724,
    "default_branch": "master",
    "updated_at": "2025-07-12T21:58:19Z",
    "clones": 26,
    "uniques": 24,
    "views": 81,
    "visitors": 10,
    "pulls_count": 0,
    "fetched": "2025-07-16T21:01:02.612867"
  },
  {
    "repo": "AscendNet",
    "stars": 6,
    "forks": 0,
    "watchers": 2,
    "open_issues": 0,
    "language": "Go",
    "size_kb": 126625,
    "default_branch": "master",
    "updated_at": "2025-07-13T18:17:43Z",
    "clones": 55,
    "uniques": 44,
    "views": 95,
    "visitors": 6,
    "pulls_count": 0,
    "fetched": "2025-07-16T21:01:03.391656"
  },
  {
    "repo": "WorkFlowRepo",
    "stars": 2,
    "forks": 1,
    "watchers": 2,
    "open_issues": 0,
    "language": null,
    "size_kb": 1729621,
    "default_branch": "master",
    "updated_at": "2025-07-08T15:27:36Z",
    "clones": 905,
    "uniques": 95,
    "views": 116,
    "visitors": 3,
    "pulls_count": 0,
    "fetched": "2025-07-16T21:01:04.018362"
  }
]